aws_dsf/__init__.py
aws_dsf/py.typed
aws_dsf/_jsii/__init__.py
aws_dsf/_jsii/aws-dsf@1.0.0-rc.9.jsii.tgz
aws_dsf/consumption/__init__.py
aws_dsf/governance/__init__.py
aws_dsf/processing/__init__.py
aws_dsf/storage/__init__.py
aws_dsf/utils/__init__.py
aws_dsf-1.0.0rc9.dist-info/LICENSE
aws_dsf-1.0.0rc9.dist-info/METADATA
aws_dsf-1.0.0rc9.dist-info/WHEEL
aws_dsf-1.0.0rc9.dist-info/top_level.txt
aws_dsf-1.0.0rc9.dist-info/RECORD
